Workbook

Sheet Assumptions
A1: Egg Demand Forecasting Model — Assumptions & Key Results
A3: MODEL ASSUMPTIONS
A4: Selling price per unit (p) | B4: 4 | C4: $ per egg
A5: Cost per unit (c) | B5: 0.8 | C5: $ per egg
A6: Salvage value (s) | B6: 0 | C6: No recovery on unsold units
A7: Moving average window | B7: 4 | C7: Periods (weeks)
A8: Exp. smoothing alpha (α) | B8: 0.2 | C8: Weight on most recent observation
A9: Service level target | B9: 80% | C9: SL = (p-c)/(p-s) = (4-0.8)/(4-0) = 0.8
A10: Training period | B10: Weeks 1–301 | C10: Model fitting
A11: Forecast period | B11: Weeks 302+ | C11: Out-of-sample with SL buffer
A13: KEY RESULTS (Training Period: Weeks 1–301)
A14: Metric | B14: Moving Average | C14: Exp. Smoothing (α=0.2)
A15: Avg forecast error | B15: ='Data & Models'!D504 -> 11.372054 | C15: ='Data & Models'!I504 -> 20.908855
A16: Stdev forecast error | B16: ='Data & Models'!D505 -> 339.80717 | C16: ='Data & Models'!I505 -> 314.4908
A17: Min forecast error | B17: ='Data & Models'!D506 -> -712.25 | C17: ='Data & Models'!I506 -> -619.41415
A18: Max forecast error | B18: ='Data & Models'!D507 -> 768.75 | C18: ='Data & Models'!I507 -> 690.67558
A19: Avg weekly profit | B19: ='Data & Models'!D508 -> 11707.158 | C19: N/A — see SL Forecast sheet

Sheet Data & Models
A1: MOVING AVERAGE MODEL (4-period window) | H1: EXP. SMOOTHING (α = 0.20)
A2: Week | B2: Demand | C2: MA Forecast | D2: Forecast Error | E2: Order Qty (Q) | F2: Profit ($) | H2: Exp Forecast | I2: Forecast Error
A3: 1 | B3: 1974 | H3: 1974
A4: 2 | B4: 1919 | H4: =0.2*B3+0.8*H3 -> 1974 | I4: =B4-H4 -> -55
A5: 3 | B5: 1731 | H5: =0.2*B4+0.8*H4 -> 1963 | I5: =B5-H5 -> -232
A6: 4 | B6: 1668 | H6: =0.2*B5+0.8*H5 -> 1916.6 | I6: =B6-H6 -> -248.6
A7: 5 | B7: 1895 | C7: =AVERAGE(B3:B6) -> 1823 | D7: =B7-C7 -> 72 | E7: =$C$502+D7 -> 3956.5 | F7: =4*MIN(E7,$E$509)-0.8*$E$509 -> 12056.983 | H7: =0.2*B6+0.8*H6 -> 1866.88 | I7: =B7-H7 -> 28.12
A8: 6 | B8: 2369 | C8: =AVERAGE(B4:B7) -> 1803.25 | D8: =B8-C8 -> 565.75 | E8: =$C$502+D8 -> 4450.25 | F8: =4*MIN(E8,$E$509)-0.8*$E$509 -> 12056.983 | H8: =0.2*B7+0.8*H7 -> 1872.504 | I8: =B8-H8 -> 496.496
A9: 7 | B9: 1606 | C9: =AVERAGE(B5:B8) -> 1915.75 | D9: =B9-C9 -> -309.75 | E9: =$C$502+D9 -> 3574.75 | F9: =4*MIN(E9,$E$509)-0.8*$E$509 -> 11284.754 | H9: =0.2*B8+0.8*H8 -> 1971.8032 | I9: =B9-H9 -> -365.8032
A10: 8 | B10: 2468 | C10: =AVERAGE(B6:B9) -> 1884.5 | D10: =B10-C10 -> 583.5 | E10: =$C$502+D10 -> 4468 | F10: =4*MIN(E10,$E$509)-0.8*$E$509 -> 12056.983 | H10: =0.2*B9+0.8*H9 -> 1898.6426 | I10: =B10-H10 -> 569.35744
A11: 9 | B11: 2168 | C11: =AVERAGE(B7:B10) -> 2084.5 | D11: =B11-C11 -> 83.5 | E11: =$C$502+D11 -> 3968 | F11: =4*MIN(E11,$E$509)-0.8*$E$509 -> 12056.983 | H11: =0.2*B10+0.8*H10 -> 2012.514 | I11: =B11-H11 -> 155.48595
A12: 10 | B12: 2535 | C12: =AVERAGE(B8:B11) -> 2152.75 | D12: =B12-C12 -> 382.25 | E12: =$C$502+D12 -> 4266.75 | F12: =4*MIN(E12,$E$509)-0.8*$E$509 -> 12056.983 | H12: =0.2*B11+0.8*H11 -> 2043.6112 | I12: =B12-H12 -> 491.38876
A13: 11 | B13: 1835 | C13: =AVERAGE(B9:B12) -> 2194.25 | D13: =B13-C13 -> -359.25 | E13: =$C$502+D13 -> 3525.25 | F13: =4*MIN(E13,$E$509)-0.8*$E$509 -> 11086.754 | H13: =0.2*B12+0.8*H12 -> 2141.889 | I13: =B13-H13 -> -306.88899
A14: 12 | B14: 2355 | C14: =AVERAGE(B10:B13) -> 2251.5 | D14: =B14-C14 -> 103.5 | E14: =$C$502+D14 -> 3988 | F14: =4*MIN(E14,$E$509)-0.8*$E$509 -> 12056.983 | H14: =0.2*B13+0.8*H13 -> 2080.5112 | I14: =B14-H14 -> 274.48881
A15: 13 | B15: 1640 | C15: =AVERAGE(B11:B14) -> 2223.25 | D15: =B15-C15 -> -583.25 | E15: =$C$502+D15 -> 3301.25 | F15: =4*MIN(E15,$E$509)-0.8*$E$509 -> 10190.754 | H15: =0.2*B14+0.8*H14 -> 2135.409 | I15: =B15-H15 -> -495.40895
A16: 14 | B16: 2026 | C16: =AVERAGE(B12:B15) -> 2091.25 | D16: =B16-C16 -> -65.25 | E16: =$C$502+D16 -> 3819.25 | F16: =4*MIN(E16,$E$509)-0.8*$E$509 -> 12056.983 | H16: =0.2*B15+0.8*H15 -> 2036.3272 | I16: =B16-H16 -> -10.327163
A17: 15 | B17: 2209 | C17: =AVERAGE(B13:B16) -> 1964 | D17: =B17-C17 -> 245 | E17: =$C$502+D17 -> 4129.5 | F17: =4*MIN(E17,$E$509)-0.8*$E$509 -> 12056.983 | H17: =0.2*B16+0.8*H16 -> 2034.2617 | I17: =B17-H17 -> 174.73827
A18: 16 | B18: 1845 | C18: =AVERAGE(B14:B17) -> 2057.5 | D18: =B18-C18 -> -212.5 | E18: =$C$502+D18 -> 3672 | F18: =4*MIN(E18,$E$509)-0.8*$E$509 -> 11673.754 | H18: =0.2*B17+0.8*H17 -> 2069.2094 | I18: =B18-H18 -> -224.20938
... A502: 500 | B502: 4065 | C502: =AVERAGE(B498:B501) -> 3884.5 | D502: =B502-C502 -> 180.5 | E502: =$C$502+D502 -> 4065 | F502: =4*MIN(E502,$E$509)-0.8*$E$509 -> 12056.983 | H502: =0.2*B501+0.8*H501 -> 3924.1166 | I502: =B502-H502 -> 140.88339
A504: Avg forecast error | D504: =AVERAGE(D3:D303) -> 11.372054 | I504: =AVERAGE(I3:I303) -> 20.908855
A505: Stdev forecast error | D505: =STDEV(D3:D303) -> 339.80717 | I505: =STDEV(I3:I303) -> 314.4908
A506: Min forecast error | D506: =MIN(D3:D303) -> -712.25 | I506: =MIN(I3:I303) -> -619.41415
A507: Max forecast error | D507: =MAX(D3:D303) -> 768.75 | I507: =MAX(I3:I303) -> 690.67558
A508: Avg weekly profit | D508: =AVERAGE(F3:F303) -> 11707.158 | I508: "N/A"
A509: Optimal Order Qty (MA) = Week 301 Forecast + Stdev(Errors) | D509: =C303+STDEV(D3:D303) -> 3767.8072 | E509: =C303+STDEV(D3:D303) -> 3767.8072

Sheet SL Forecast
A1: SERVICE LEVEL FORECAST (Exp. Smoothing Base + 80th Percentile Buffer)
A2: Week | B2: Demand | C2: Exp Forecast | D2: Forecast Error | E2: SL Buffer (80th pct) | F2: Order Qty (Q) | G2: Profit ($)
A3: 1 | B3: 1974 | C3: 1974
A4: 2 | B4: 1919 | C4: =0.2*B3+0.8*C3 -> 1974 | D4: =B4-C4 -> -55
A5: 3 | B5: 1731 | C5: =0.2*B4+0.8*C4 -> 1963 | D5: =B5-C5 -> -232 | E5: =PERCENTILE(D$4:D5,0.8) -> -90.4 | F5: =C5+E5 -> 1872.6 | G5: =4*MIN(F5,B5)-0.8*F5 -> 5425.92
A6: 4 | B6: 1668 | C6: =0.2*B5+0.8*C5 -> 1916.6 | D6: =B6-C6 -> -248.6 | E6: =PERCENTILE(D$4:D6,0.8) -> -125.8 | F6: =C6+E6 -> 1790.8 | G6: =4*MIN(F6,B6)-0.8*F6 -> 5239.36
A7: 5 | B7: 1895 | C7: =0.2*B6+0.8*C6 -> 1866.88 | D7: =B7-C7 -> 28.12 | E7: =PERCENTILE(D$4:D7,0.8) -> -21.752 | F7: =C7+E7 -> 1845.128 | G7: =4*MIN(F7,B7)-0.8*F7 -> 5904.4096
A8: 6 | B8: 2369 | C8: =0.2*B7+0.8*C7 -> 1872.504 | D8: =B8-C8 -> 496.496 | E8: =PERCENTILE(D$4:D8,0.8) -> 121.7952 | F8: =C8+E8 -> 1994.2992 | G8: =4*MIN(F8,B8)-0.8*F8 -> 6381.7574
A9: 7 | B9: 1606 | C9: =0.2*B8+0.8*C8 -> 1971.8032 | D9: =B9-C9 -> -365.8032 | E9: =PERCENTILE(D$4:D9,0.8) -> 28.12 | F9: =C9+E9 -> 1999.9232 | G9: =4*MIN(F9,B9)-0.8*F9 -> 4824.0614
A10: 8 | B10: 2468 | C10: =0.2*B9+0.8*C9 -> 1898.6426 | D10: =B10-C10 -> 569.35744 | E10: =PERCENTILE(D$4:D10,0.8) -> 402.8208 | F10: =C10+E10 -> 2301.4634 | G10: =4*MIN(F10,B10)-0.8*F10 -> 7364.6828
A11: 9 | B11: 2168 | C11: =0.2*B10+0.8*C10 -> 2012.514 | D11: =B11-C11 -> 155.48595 | E11: =PERCENTILE(D$4:D11,0.8) -> 360.09198 | F11: =C11+E11 -> 2372.606 | G11: =4*MIN(F11,B11)-0.8*F11 -> 6773.9152
A12: 10 | B12: 2535 | C12: =0.2*B11+0.8*C11 -> 2043.6112 | D12: =B12-C12 -> 491.38876 | E12: =PERCENTILE(D$4:D12,0.8) -> 493.43166 | F12: =C12+E12 -> 2537.0429 | G12: =4*MIN(F12,B12)-0.8*F12 -> 8110.3657
A13: 11 | B13: 1835 | C13: =0.2*B12+0.8*C12 -> 2141.889 | D13: =B13-C13 -> -306.88899 | E13: =PERCENTILE(D$4:D13,0.8) -> 492.41021 | F13: =C13+E13 -> 2634.2992 | G13: =4*MIN(F13,B13)-0.8*F13 -> 5232.5606
A14: 12 | B14: 2355 | C14: =0.2*B13+0.8*C13 -> 2080.5112 | D14: =B14-C14 -> 274.48881 | E14: =PERCENTILE(D$4:D14,0.8) -> 491.38876 | F14: =C14+E14 -> 2571.9 | G14: =4*MIN(F14,B14)-0.8*F14 -> 7362.48
A15: 13 | B15: 1640 | C15: =0.2*B14+0.8*C14 -> 2135.409 | D15: =B15-C15 -> -495.40895 | E15: =PERCENTILE(D$4:D15,0.8) -> 448.00877 | F15: =C15+E15 -> 2583.4177 | G15: =4*MIN(F15,B15)-0.8*F15 -> 4493.2658
A16: 14 | B16: 2026 | C16: =0.2*B15+0.8*C15 -> 2036.3272 | D16: =B16-C16 -> -10.327163 | E16: =PERCENTILE(D$4:D16,0.8) -> 404.62878 | F16: =C16+E16 -> 2440.9559 | G16: =4*MIN(F16,B16)-0.8*F16 -> 6151.2352
... A502: 500 | B502: 4065 | C502: =0.2*B501+0.8*C501 -> 3924.1166 | D502: =B502-C502 -> 140.88339 | E502: =PERCENTILE(D$4:D502,0.8) -> 318.15663 | F502: =C502+E502 -> 4242.2732 | G502: =4*MIN(F502,B502)-0.8*F502 -> 12866.181
A504: Avg Weekly Profit (SL Model) | G504: =AVERAGE(G5:G502) -> 9326.8027
